{
  "primary": {
    "lighter": "#E3F2FD",
    "light": "#90CAF9",
    "main": "#2196F3",
    "dark": "#1565C0",
    "darker": "#0D47A1",
    "contrastText": "#FFFFFF"
  },
  "secondary": {
    "lighter": "#F5F5F6",
    "light": "#B0BEC5",
    "main": "#607D8B",
    "dark": "#455A64",
    "darker": "#263238",
    "contrastText": "#FFFFFF"
  },
  "info": {
    "lighter": "#E1F5FE",
    "light": "#81D4FA",
    "main": "#03A9F4",
    "dark": "#0277BD",
    "darker": "#01579B",
    "contrastText": "#FFFFFF"
  },
  "success": {
    "lighter": "#E8F5E8",
    "light": "#A5D6A7",
    "main": "#4CAF50",
    "dark": "#388E3C",
    "darker": "#2E7D32",
    "contrastText": "#ffffff"
  },
  "warning": {
    "lighter": "#FFF8E1",
    "light": "#FFD54F",
    "main": "#FF9800",
    "dark": "#F57C00",
    "darker": "#E65100",
    "contrastText": "#FFFFFF"
  },
  "error": {
    "lighter": "#FFEBEE",
    "light": "#EF9A9A",
    "main": "#F44336",
    "dark": "#D32F2F",
    "darker": "#C62828",
    "contrastText": "#FFFFFF"
  },
  "grey": {
    "50": "#FAFAFA",
    "100": "#F5F5F5",
    "200": "#EEEEEE",
    "300": "#E0E0E0",
    "400": "#BDBDBD",
    "500": "#9E9E9E",
    "600": "#757575",
    "700": "#616161",
    "800": "#424242",
    "900": "#212121"
  },
  "common": {
    "black": "#000000",
    "white": "#FFFFFF"
  }
}
